{
  "permit_id": "25098458.0",
  "business_name": "Granite Properties",
  "dba": "",
  "phone": "",
  "website": "3355westalabama.com",
  "industry_guess": "Office",
  "confidence": "medium",
  "source_url": "https://3355westalabama.com/",
  "notes": "3355 W Alabama is a Granite Properties building (236,932 SF, class B office). Known tenants include GSA and Fairgrounds Management Co, but no specific tenant identified for Suite 450. The permit is likely a spec suite buildout by the landlord for a future tenant.",
  "ts": "2026-04-13T01:55:22.310701+00:00"
}