{
  "permit_id": "BLDC-2026-00083",
  "business_name": "",
  "dba": "",
  "phone": "",
  "website": "",
  "industry_guess": "Gym / Fitness",
  "confidence": "low",
  "source_url": "https://fitnessconnection.com/gyms/mission-bend",
  "notes": "3003 Highway 6 S, Houston TX 77082. TI for fitness/gym at 6200 sqft. No exact-address tenant match found. Fitness Connection Mission Bend is in the same Highway 6 corridor but at a different address. Specific tenant not confirmed.",
  "ts": "2026-05-11T00:00:00Z"
}