{
  "permit_id": "ELEC-2026-00157",
  "business_name": "Carmelo's Mexican Grill",
  "dba": "Carmelos",
  "phone": "(281) 494-2031",
  "website": "",
  "industry_guess": "Retail — Restaurant/Bar",
  "confidence": "high",
  "source_url": "https://www.yelp.com/biz/carmelos-mexican-grill-sugar-land",
  "notes": "Carmelo's Mexican Grill is an established Mexican restaurant in Sugar Land on Hwy 90A; permit description names 'CARMELOS' for a kitchen remodel/replacement at 5010 US 90A.",
  "ts": "2026-05-18T00:00:00Z"
}
