{
  "permit_id": "{5E86B3BA-0C23-45E6-89B2-DE391D9AA71E}",
  "business_name": "",
  "dba": "Jordan Ranch Plaza",
  "phone": "",
  "website": "https://theretailconnection.net/properties/plaza-at-jordan-ranch-katy-tx/",
  "industry_guess": "Retail",
  "confidence": "medium",
  "source_url": "https://theretailconnection.net/properties/plaza-at-jordan-ranch-katy-tx/",
  "notes": "Plaza at Jordan Ranch is a retail center in the Jordan Ranch master-planned community near Katy TX 77423, brokered by The Retail Connection; no specific anchor tenant confirmed but retail strip/neighborhood center use is well supported.",
  "ts": "2026-05-15T00:00:00Z"
}