{
  "permit_id": "{C695FEA3-860A-4645-9150-0324F1C45DB0}",
  "business_name": "H-E-B",
  "dba": "",
  "phone": "(832) 595-5337",
  "website": "https://www.heb.com/heb-store/US/tx/richmond/richmond-market-h-e-b-727",
  "industry_guess": "Retail",
  "confidence": "medium",
  "source_url": "https://www.heb.com/heb-store/US/tx/richmond/richmond-market-h-e-b-727",
  "notes": "Circle Oak is a large mixed-use development in Richmond TX 77469; H-E-B Richmond Market at 23500 Circle Oak Pkwy is the anchor commercial tenant. Development also includes The Ryon apartments (348 units) and Kelsey Seybold medical clinic.",
  "ts": "2026-05-14T12:00:00Z"
}
